mcp_agent_tools/__init__.py
mcp_agent_tools/exceptions.py
mcp_agent_tools/mcp_tool_service.py
mcp_agent_tools/models.py
mcp_agent_tools/smol_mcp_tool_factory.py
mcp_agent_tools/smol_tool_converter.py
mcp_agent_tools-0.1.0.dist-info/licenses/LICENSE
mcp_agent_tools-0.1.0.dist-info/METADATA
mcp_agent_tools-0.1.0.dist-info/WHEEL
mcp_agent_tools-0.1.0.dist-info/top_level.txt
mcp_agent_tools-0.1.0.dist-info/RECORD
