Metadata-Version: 2.4
Name: mcp_agent_tools
Version: 0.1.0
Summary: Tools for integrating with MCP servers for AI agents
Home-page: https://github.com/esragoth/mcp_agent_tools
Author: esragoth
Author-email: ESRagoth <beppe.wizzy@gmail.com>
License: MIT
Project-URL: Homepage, https://github.com/esragoth/mcp_agent_tools
Project-URL: Bug Tracker, https://github.com/esragoth/mcp_agent_tools/issues
Classifier: Programming Language :: Python :: 3
Classifier: License :: OSI Approved :: MIT License
Classifier: Operating System :: OS Independent
Requires-Python: >=3.10
License-File: LICENSE
Requires-Dist: aiohttp
Requires-Dist: websockets
Requires-Dist: pydantic>=2.0.0
Requires-Dist: mcp
Provides-Extra: dev
Requires-Dist: pytest; extra == "dev"
Requires-Dist: black; extra == "dev"
Requires-Dist: isort; extra == "dev"
Requires-Dist: mypy; extra == "dev"
Provides-Extra: smolagents
Requires-Dist: smolagents; extra == "smolagents"
Dynamic: author
Dynamic: home-page
Dynamic: license-file
Dynamic: requires-python
